README.rst
setup.py
Slot_Client.egg-info/PKG-INFO
Slot_Client.egg-info/SOURCES.txt
Slot_Client.egg-info/dependency_links.txt
Slot_Client.egg-info/entry_points.txt
Slot_Client.egg-info/requires.txt
Slot_Client.egg-info/top_level.txt
request/__init__.py
request/create_project_request.py
request/project_operator_request.py
request/update_project_request.py
request/upload_file_request.py
response/__init__.py
response/cm_info.py
response/details.py
response/file.py
response/file_type.py
response/files.py
response/meta_info.py
response/pm_info.py
response/project.py
response/project_operator.py
response/upload_file_info.py
response/upload_user.py